{
  "schemaVersion": "rigor.preflight.v1",
  "artifactId": "preflight_42f25335-ab6b-48ea-b600-89d216f3f488",
  "taskId": "GH-26-R3",
  "createdAt": "2026-07-13T02:41:01.329Z",
  "policyHash": "30226d434cef2438f1514a1cc0a32f0038fb05810213b02f776d316983d29011",
  "intentHash": "221e06a4d143775c79e6ca0a27893e44dc5cc8f778b00aac4d67dd78f0a3541f",
  "git": {
    "root": "/Users/xhn/src/private/rigor",
    "head": "2e1160cd70d7fc1ed032a921c9c7d93be3056821",
    "dirty": true,
    "changedPaths": [
      ".github/workflows/consumer-portability.yml",
      ".rigor/evidence/GH-26-R2/contract.json",
      ".rigor/evidence/GH-26-R2/preflight.json",
      ".rigor/evidence/GH-26-R2/verification.json",
      "docs/adr/0001-provenance-trust-model.md",
      "docs/provenance.md",
      "docs/threat-model.md",
      "scripts/install-verified.mjs",
      "scripts/package-plugin.mjs",
      "test/provenance.test.ts"
    ]
  },
  "plannedPaths": [
    ".github/workflows/consumer-portability.yml",
    "docs/adr/0001-provenance-trust-model.md",
    "docs/provenance.md",
    "docs/threat-model.md",
    "scripts/install-verified.mjs",
    "scripts/package-plugin.mjs",
    "test/provenance.test.ts"
  ],
  "riskTier": "critical",
  "externalTransmission": "allowed",
  "protectedPaths": [
    ".github/workflows/consumer-portability.yml"
  ],
  "requireHumanApproval": true,
  "stopConditions": [
    "scope expands beyond the contract",
    "an irreversible or external write is needed",
    "credentials or personal data are encountered",
    "independent human approval is unavailable"
  ],
  "reasons": [
    {
      "ruleId": "governance",
      "path": ".github/workflows/consumer-portability.yml",
      "reason": "Governance and enforcement changes can weaken controls."
    },
    {
      "ruleId": "tests-and-docs",
      "path": "docs/adr/0001-provenance-trust-model.md",
      "reason": "Tests and documentation normally have limited direct runtime impact."
    },
    {
      "ruleId": "tests-and-docs",
      "path": "docs/provenance.md",
      "reason": "Tests and documentation normally have limited direct runtime impact."
    },
    {
      "ruleId": "tests-and-docs",
      "path": "docs/threat-model.md",
      "reason": "Tests and documentation normally have limited direct runtime impact."
    },
    {
      "ruleId": "tests-and-docs",
      "path": "test/provenance.test.ts",
      "reason": "Tests and documentation normally have limited direct runtime impact."
    },
    {
      "ruleId": "dirty-worktree",
      "reason": "The worktree already contains changes that can affect evidence."
    }
  ]
}
